geocaching_utils/__init__.py
geocaching_utils/cli/__init__.py
geocaching_utils/cli/convert_coords.py
geocaching_utils/cli/decode_cipher.py
geocaching_utils/cli/geometry_calc.py
geocaching_utils/cli/main.py
geocaching_utils/cli/puzzle_tools.py
geocaching_utils/data/public/geocaching-utils-logo.png
geocaching_utils/data/sample_puzzles/puzzle1.txt
geocaching_utils/tests/__init__.py
geocaching_utils/tests/test_ciphers.py
geocaching_utils/tests/test_coordinates.py
geocaching_utils/tests/test_geometry.py
geocaching_utils/tests/test_puzzle_helpers.py
geocaching_utils/utils/__init__.py
geocaching_utils/utils/ciphers.py
geocaching_utils/utils/coordinates.py
geocaching_utils/utils/geometry.py
geocaching_utils/utils/puzzle_helpers.py
geocaching_utils-0.1.1.dist-info/LICENSE
geocaching_utils-0.1.1.dist-info/METADATA
geocaching_utils-0.1.1.dist-info/WHEEL
geocaching_utils-0.1.1.dist-info/entry_points.txt
geocaching_utils-0.1.1.dist-info/top_level.txt
geocaching_utils-0.1.1.dist-info/RECORD
