Metadata-Version: 2.2
Name: geocaching-utils
Version: 0.1.1
Summary: A collection of utilities for geocaching puzzle solving
Author-email: geocaching-Utils Team <hytegeocaching@gmail.com>
License: MIT
Project-URL: Homepage, https://github.com/spectraldecomp/geocaching-utils
Project-URL: Bug Tracker, https://github.com/spectraldecomp/geocaching-utils/issues
Classifier: Programming Language :: Python :: 3
Classifier: License :: OSI Approved :: MIT License
Classifier: Operating System :: OS Independent
Classifier: Development Status :: 3 - Alpha
Classifier: Intended Audience :: End Users/Desktop
Classifier: Topic :: Utilities
Requires-Python: >=3.6
License-File: LICENSE
